sqlalchemy_unchained/__init__.py
sqlalchemy_unchained/alembic_templates/generic/README
sqlalchemy_unchained/alembic_templates/generic/alembic.ini.mako
sqlalchemy_unchained/alembic_templates/generic/env.py
sqlalchemy_unchained/alembic_templates/generic/script.py.mako
sqlalchemy_unchained/base_model.py
sqlalchemy_unchained/base_model_metaclass.py
sqlalchemy_unchained/cli.py
sqlalchemy_unchained/foreign_key.py
sqlalchemy_unchained/model_manager.py
sqlalchemy_unchained/model_meta_options.py
sqlalchemy_unchained/model_registry.py
sqlalchemy_unchained/py.typed
sqlalchemy_unchained/session_manager.py
sqlalchemy_unchained/utils.py
sqlalchemy_unchained/validation.py
sqlalchemy_unchained-0.14.0.dist-info/LICENSE
sqlalchemy_unchained-0.14.0.dist-info/METADATA
sqlalchemy_unchained-0.14.0.dist-info/WHEEL
sqlalchemy_unchained-0.14.0.dist-info/entry_points.txt
sqlalchemy_unchained-0.14.0.dist-info/RECORD
