Metadata-Version: 2.1
Name: sqlalchemy-unchained
Version: 0.14.0
Summary: Improved declarative SQLAlchemy models
Home-page: https://github.com/briancappello/sqlalchemy-unchained
License: MIT
Author: Brian Cappello
Requires-Python: >=3.10,<4.0
Classifier: License :: OSI Approved :: MIT License
Classifier: Programming Language :: Python :: 3
Classifier: Programming Language :: Python :: 3.10
Classifier: Programming Language :: Python :: 3.11
Classifier: Programming Language :: Python :: 3.12
Requires-Dist: alembic (>=1.11.1,<2.0.0)
Requires-Dist: py-meta-utils (>=0.8.0,<0.9.0)
Requires-Dist: sqlalchemy (>=1.3,<2)
Project-URL: Repository, https://github.com/briancappello/sqlalchemy-unchained
